{"cameraMode":{"drawMode":0,"name":"Shaded","section":"Shading Mode"},"sceneLighting":true,"audioPlay":false,"sceneViewState":{"showFog":true,"showMaterialUpdate":false,"showSkybox":true,"showFlares":true,"showImageEffects":true,"showParticleSystems":true,"showVisualEffectGraphs":true,"m_FxEnabled":false},"in2DMode":false,"pivot":{"x":-6.624622821807861,"y":-14.299957275390625,"z":9.519076347351075},"rotation":{"x":0.49013254046440127,"y":0.02091921493411064,"z":-0.01175844855606556,"w":0.8713286519050598},"size":13.251628875732422,"orthographic":false}